usb_protocol/__init__.py
usb_protocol/emitters/__init__.py
usb_protocol/emitters/construct_interop.py
usb_protocol/emitters/descriptor.py
usb_protocol/emitters/descriptors/__init__.py
usb_protocol/emitters/descriptors/cdc.py
usb_protocol/emitters/descriptors/microsoft10.py
usb_protocol/emitters/descriptors/midi1.py
usb_protocol/emitters/descriptors/standard.py
usb_protocol/emitters/descriptors/uac1.py
usb_protocol/emitters/descriptors/uac2.py
usb_protocol/emitters/descriptors/uac3.py
usb_protocol/types/__init__.py
usb_protocol/types/descriptor.py
usb_protocol/types/descriptors/__init__.py
usb_protocol/types/descriptors/cdc.py
usb_protocol/types/descriptors/microsoft10.py
usb_protocol/types/descriptors/midi1.py
usb_protocol/types/descriptors/midi2.py
usb_protocol/types/descriptors/standard.py
usb_protocol/types/descriptors/test_uac2.py
usb_protocol/types/descriptors/uac1.py
usb_protocol/types/descriptors/uac2.py
usb_protocol/types/descriptors/uac3.py
usb_protocol/types/descriptors/partial/__init__.py
usb_protocol/types/descriptors/partial/standard.py
usb_protocol/types/superspeed/__init__.py
usb_protocol-0.9.2.dist-info/licenses/LICENSE.txt
usb_protocol-0.9.2.dist-info/METADATA
usb_protocol-0.9.2.dist-info/WHEEL
usb_protocol-0.9.2.dist-info/top_level.txt
usb_protocol-0.9.2.dist-info/RECORD
