Metadata-Version: 2.4
Name: usb-protocol
Version: 0.9.2
Summary: Python library providing utilities, data structures, constants, parsers, and tools for working with the USB protocol.
Author-email: Great Scott Gadgets <dev@greatscottgadgets.com>
License: BSD
Project-URL: Documentation, https://python-usb-protocol.readthedocs.io
Project-URL: Repository, https://github.com/greatscottgadgets/python-usb-protocol
Project-URL: Issues, https://github.com/greatscottgadgets/python-usb-protocol/issues
Classifier: Development Status :: 4 - Beta
Classifier: Programming Language :: Python :: 3
Classifier: Programming Language :: Python :: 3.9
Classifier: Programming Language :: Python :: 3.10
Classifier: Programming Language :: Python :: 3.11
Classifier: Programming Language :: Python :: 3.12
Classifier: Programming Language :: Python :: 3.13
Classifier: License :: OSI Approved :: BSD License
Classifier: Operating System :: OS Independent
Classifier: Natural Language :: English
Classifier: Environment :: Console
Classifier: Environment :: Plugins
Classifier: Intended Audience :: Developers
Classifier: Intended Audience :: Science/Research
Classifier: Topic :: Scientific/Engineering :: Electronic Design Automation (EDA)
Classifier: Topic :: Security
Classifier: Topic :: System :: Hardware :: Universal Serial Bus (USB)
Requires-Python: >=3.9
License-File: LICENSE.txt
Requires-Dist: construct~=2.10
Dynamic: license-file
